vte/__init__.py
vte/__main__.py
vte/template_engine.py
vte/template_info.py
vte/template_rgy.py
vte/cmds/__init__.py
vte/cmds/generate.py
vte/cmds/list.py
vte/cmds/preprocess.py
vte/cmds/quickstart.py
vte-0.0.4.3356324653.dist-info/LICENSE
vte-0.0.4.3356324653.dist-info/METADATA
vte-0.0.4.3356324653.dist-info/WHEEL
vte-0.0.4.3356324653.dist-info/entry_points.txt
vte-0.0.4.3356324653.dist-info/top_level.txt
vte-0.0.4.3356324653.dist-info/RECORD
