Metadata-Version: 2.1
Name: vte
Version: 0.0.4.3356324653
Summary: Template-driven content generation script focused on verification
Home-page: https://github.com/mballance/vte
Author: Matthew Ballance
Author-email: matt.ballance@gmail.com
License: Apache 2.0
Keywords: SystemVerilog,Verilog,RTL,GoogleTest
License-File: LICENSE
Requires-Dist: jinja2 (>=2.10)
Requires-Dist: jinja2-strcase
Requires-Dist: pyyaml
